calculator/__init__.py
calculator/advanced_operations.py
calculator/basic_operations.py
calculator/logarithms.py
calculator/statistics.py
calculator/trigonometry.py
leonardo_floresgonzalez_calculator_5436-0.3.0.dist-info/METADATA
leonardo_floresgonzalez_calculator_5436-0.3.0.dist-info/WHEEL
leonardo_floresgonzalez_calculator_5436-0.3.0.dist-info/top_level.txt
leonardo_floresgonzalez_calculator_5436-0.3.0.dist-info/RECORD
